drf_renderer_xlsx/__init__.py
drf_renderer_xlsx/mixins.py
drf_renderer_xlsx/renderers.py
drf_renderer_xlsx_ko-1.0.dist-info/LICENSE
drf_renderer_xlsx_ko-1.0.dist-info/METADATA
drf_renderer_xlsx_ko-1.0.dist-info/WHEEL
drf_renderer_xlsx_ko-1.0.dist-info/top_level.txt
drf_renderer_xlsx_ko-1.0.dist-info/RECORD
